MANIFEST.in
README.md
VERSION
panther_classic_converter
setup.py
bin/panther_classic_converter
panther_classic_converter/__init__.py
panther_classic_converter/main.py
panther_classic_converter.egg-info/PKG-INFO
panther_classic_converter.egg-info/SOURCES.txt
panther_classic_converter.egg-info/dependency_links.txt
panther_classic_converter.egg-info/requires.txt
panther_classic_converter.egg-info/top_level.txt
panther_classic_converter/converter/__init__.py
panther_classic_converter/converter/converter.py
panther_classic_converter/converter/detection_builder.py
panther_classic_converter/converter/import_fixer.py
panther_classic_converter/converter/linter_fixer.py
panther_classic_converter/converter/name_fixer.py
tests/__init__.py
tests/test_convert_policies.py
tests/test_convert_rules.py
tests/test_convert_scheduled_queries.py
tests/test_convert_scheduled_rules.py